telegraf_pgbouncer/__init__.py
telegraf_pgbouncer/cli.py
telegraf_pgbouncer-0.3.0.dist-info/DESCRIPTION.rst
telegraf_pgbouncer-0.3.0.dist-info/METADATA
telegraf_pgbouncer-0.3.0.dist-info/RECORD
telegraf_pgbouncer-0.3.0.dist-info/WHEEL
telegraf_pgbouncer-0.3.0.dist-info/entry_points.txt
telegraf_pgbouncer-0.3.0.dist-info/metadata.json
telegraf_pgbouncer-0.3.0.dist-info/top_level.txt
telegraf_pgbouncer-0.3.0.dist-info/zip-safe
