Metadata-Version: 2.0
Name: telegraf-pgbouncer
Version: 0.3.0
Summary: pgBouncer Stats Collector for Telegraf
Home-page: https://github.com/gmr/telegraf-pgbouncer
Author: Gavin M. Roy
Author-email: gavinmroy@gmail.com
License: BSD
Keywords: static website generation
Platform: UNKNOWN
Classifier: Development Status :: 3 - Alpha
Classifier: Environment :: Console
Classifier: Intended Audience :: System Administrators
Classifier: Programming Language :: Python :: 3
Classifier: Programming Language :: Python :: 3.5
Classifier: Programming Language :: Python :: 3.6
Classifier: License :: OSI Approved :: BSD License
Classifier: Topic :: System :: Monitoring
Requires-Dist: psycopg2-binary
